aws_solutions_constructs/aws_kinesis_firehose_s3_kinesis_analytics/__init__.py
aws_solutions_constructs/aws_kinesis_firehose_s3_kinesis_analytics/py.typed
aws_solutions_constructs/aws_kinesis_firehose_s3_kinesis_analytics/_jsii/__init__.py
aws_solutions_constructs/aws_kinesis_firehose_s3_kinesis_analytics/_jsii/aws-kinesisfirehose-s3-and-kinesisanalytics@2.45.0.jsii.tgz
aws_solutions_constructs.aws_kinesis_firehose_s3_kinesis_analytics-2.45.0.dist-info/LICENSE
aws_solutions_constructs.aws_kinesis_firehose_s3_kinesis_analytics-2.45.0.dist-info/METADATA
aws_solutions_constructs.aws_kinesis_firehose_s3_kinesis_analytics-2.45.0.dist-info/WHEEL
aws_solutions_constructs.aws_kinesis_firehose_s3_kinesis_analytics-2.45.0.dist-info/top_level.txt
aws_solutions_constructs.aws_kinesis_firehose_s3_kinesis_analytics-2.45.0.dist-info/RECORD
