Metadata-Version: 2.1
Name: aws-solutions-constructs.aws-kinesis-firehose-s3-kinesis-analytics
Version: 2.45.0
Summary: CDK constructs for defining an interaction between an Amazon Kinesis Data Firehose delivery stream and (1) an Amazon S3 bucket, and (2) an Amazon Kinesis Data Analytics application.
Home-page: https://github.com/awslabs/aws-solutions-constructs.git
Author: Amazon Web Services
License: Apache-2.0
Project-URL: Source, https://github.com/awslabs/aws-solutions-constructs.git
Classifier: Intended Audience :: Developers
Classifier: Operating System :: OS Independent
Classifier: Programming Language :: JavaScript
Classifier: Programming Language :: Python :: 3 :: Only
Classifier: Programming Language :: Python :: 3.7
Classifier: Programming Language :: Python :: 3.8
Classifier: Programming Language :: Python :: 3.9
Classifier: Programming Language :: Python :: 3.10
Classifier: Programming Language :: Python :: 3.11
Classifier: Typing :: Typed
Classifier: License :: OSI Approved
Requires-Python: ~=3.7
License-File: LICENSE
Requires-Dist: aws-cdk-lib <3.0.0,>=2.99.1
Requires-Dist: aws-solutions-constructs.aws-kinesis-firehose-s3 ==2.45.0
Requires-Dist: aws-solutions-constructs.core ==2.45.0
Requires-Dist: constructs <11.0.0,>=10.0.0
Requires-Dist: jsii <2.0.0,>=1.90.0
Requires-Dist: publication >=0.0.3
Requires-Dist: typeguard ~=2.13.3
